example_pkg/__init__.py
PlantTraitEnrichment-1.0.1.dist-info/LICENSE
PlantTraitEnrichment-1.0.1.dist-info/METADATA
PlantTraitEnrichment-1.0.1.dist-info/WHEEL
PlantTraitEnrichment-1.0.1.dist-info/top_level.txt
PlantTraitEnrichment-1.0.1.dist-info/RECORD
