Metadata-Version: 2.1
Name: PlantTraitEnrichment
Version: 1.0.1
Summary: A python package for plant trait enrichment analysis.
Home-page: https://github.com/YaoXinZhi/Plant-Trait-Enrichment
Author: Xinzhi_Yao
Author-email: xinzhi_bioinfo@163.com
License: UNKNOWN
Platform: UNKNOWN
Classifier: Programming Language :: Python :: 3
Classifier: License :: OSI Approved :: MIT License
Classifier: Operating System :: OS Independent
